pyloco_task_show/__init__.py
pyloco_task_show/show.py
pyloco_task_show-0.0.1.dist-info/METADATA
pyloco_task_show-0.0.1.dist-info/WHEEL
pyloco_task_show-0.0.1.dist-info/entry_points.txt
pyloco_task_show-0.0.1.dist-info/top_level.txt
pyloco_task_show-0.0.1.dist-info/RECORD
