Metadata-Version: 2.1
Name: pyloco-task-show
Version: 0.0.1
Summary: UNKNOWN
Home-page: UNKNOWN
Author: UNKNOWN
Author-email: UNKNOWN
License: UNKNOWN
Platform: UNKNOWN
Requires-Dist: pyloco
